resumable_file_server.py
resumable_file_server-0.1.0a1.dist-info/licenses/LICENSE
resumable_file_server-0.1.0a1.dist-info/METADATA
resumable_file_server-0.1.0a1.dist-info/WHEEL
resumable_file_server-0.1.0a1.dist-info/top_level.txt
resumable_file_server-0.1.0a1.dist-info/RECORD
