Metadata-Version: 2.4
Name: resumable-file-server
Version: 0.1.0a1
Summary: A simple, multithreaded HTTP file server supporting resumable downloads and file uploads written in pure Python. Drop-in replacement for `SimpleHTTPServer`, `http.server`.
Author-email: Jifeng Wu <jifengwu2k@gmail.com>
License-Expression: MIT
Project-URL: Homepage, https://github.com/jifengwu2k/resumable-file-server
Project-URL: Bug Tracker, https://github.com/jifengwu2k/resumable-file-server/issues
Classifier: Programming Language :: Python :: 2
Classifier: Programming Language :: Python :: 3
Classifier: Operating System :: OS Independent
Requires-Python: >=2
License-File: LICENSE
Requires-Dist: guess-file-mime-type
Requires-Dist: textcompat
Dynamic: license-file
